README.md
setup.cfg
setup.py
ohadlibs/__init__.py
ohadlibs.egg-info/PKG-INFO
ohadlibs.egg-info/SOURCES.txt
ohadlibs.egg-info/dependency_links.txt
ohadlibs.egg-info/requires.txt
ohadlibs.egg-info/top_level.txt
ohadlibs/common/__init__.py
ohadlibs/common/tools.py
ohadlibs/connectivity/__init__.py
ohadlibs/connectivity/consoles.py
ohadlibs/connectivity/third_parties/__init__.py
ohadlibs/connectivity/third_parties/python_ssh.py
ohadlibs/data/__init__.py
ohadlibs/data/files/__init__.py
ohadlibs/data/files/hashing.py
ohadlibs/data/parsing/__init__.py
ohadlibs/data/parsing/xml.py
ohadlibs/data/scraping/__init__.py
ohadlibs/data/scraping/accessories.py
ohadlibs/data/scraping/scrapers.py
ohadlibs/databases/__init__.py
ohadlibs/databases/access_api.py
ohadlibs/databases/base.py
ohadlibs/gui/__init__.py
ohadlibs/gui/automation/__init__.py
ohadlibs/gui/automation/visible_interaction.py
ohadlibs/gui/automation/selenium/__init__.py
ohadlibs/gui/automation/selenium/forms.py
ohadlibs/gui/automation/selenium/select.py
ohadlibs/gui/tkinter/__init__.py
ohadlibs/gui/tkinter/widgets.py
ohadlibs/runtime/__init__.py
ohadlibs/runtime/cache.py
ohadlibs/runtime/memory.py
ohadlibs/runtime/logger/__init__.py
ohadlibs/runtime/logger/log.py